{
  "grand hyatt seoul": {
    "price": 1800,
    "name": "Grand Hyatt Seoul",
    "all_time_low": 179,
    "updated": "2025-12-29"
  },
  "fairmont ambassador seoul": {
    "price": 277,
    "name": "Fairmont Ambassador Seoul",
    "all_time_low": 276,
    "updated": "2025-12-29"
  },
  "the shilla seoul": {
    "price": 277,
    "name": "The Shilla Seoul",
    "all_time_low": 276,
    "updated": "2025-12-29"
  },
  "signiel seoul": {
    "price": 296,
    "name": "SIGNIEL SEOUL",
    "all_time_low": 294,
    "updated": "2025-12-29"
  },
  "grand intercontinental seoul parnas": {
    "price": 304,
    "name": "Grand InterContinental Seoul Parnas",
    "all_time_low": 303,
    "updated": "2025-12-29"
  },
  "conrad seoul": {
    "price": 311,
    "name": "Conrad Seoul",
    "all_time_low": 310,
    "updated": "2025-12-29"
  },
  "park hyatt seoul": {
    "price": 346,
    "name": "Park Hyatt Seoul",
    "all_time_low": 345,
    "updated": "2025-12-29"
  },
  "four seasons hotel seoul": {
    "price": 443,
    "name": "Four Seasons Hotel Seoul",
    "all_time_low": 441,
    "updated": "2025-12-29"
  },
  "paradise hotel busan": {
    "price": 166,
    "name": "Paradise Hotel Busan",
    "all_time_low": 165,
    "updated": "2025-12-29"
  },
  "signiel busan": {
    "price": 214,
    "name": "SIGNIEL BUSAN",
    "all_time_low": 213,
    "updated": "2025-12-29"
  },
  "jw marriott jeju resort spa": {
    "price": 623,
    "name": "JW Marriott Jeju Resort & Spa",
    "all_time_low": 621,
    "updated": "2025-12-29"
  }
}
