{
  "grand hyatt seoul": {
    "price": 148,
    "name": "Grand Hyatt Seoul",
    "earliest": "2027-02-01",
    "all_time_low": 137,
    "updated": "2026-06-16",
    "credit": 100,
    "credit_inferred": true
  },
  "the shilla seoul": {
    "price": 263,
    "name": "The Shilla Seoul",
    "earliest": "2027-01-04",
    "all_time_low": 256,
    "updated": "2026-06-16",
    "credit": 100,
    "credit_inferred": true
  },
  "fairmont ambassador seoul": {
    "price": 296,
    "name": "Fairmont Ambassador Seoul",
    "earliest": "2026-08-17",
    "all_time_low": 242,
    "updated": "2026-06-16",
    "credit": 100,
    "credit_inferred": true
  },
  "signiel seoul": {
    "price": 336,
    "name": "SIGNIEL SEOUL",
    "earliest": "2026-08-18",
    "all_time_low": 256,
    "updated": "2026-06-16",
    "credit": 100,
    "credit_inferred": true
  },
  "conrad seoul": {
    "price": 332,
    "name": "Conrad Seoul",
    "earliest": "2027-01-04",
    "all_time_low": 280,
    "updated": "2026-06-16",
    "credit": 100,
    "credit_inferred": true
  },
  "grand intercontinental seoul parnas": {
    "price": 322,
    "name": "Grand InterContinental Seoul Parnas",
    "earliest": "2026-08-17",
    "all_time_low": 256,
    "updated": "2026-06-16",
    "credit": 100,
    "credit_inferred": true
  },
  "park hyatt seoul": {
    "price": 355,
    "name": "Park Hyatt Seoul",
    "earliest": "2026-08-17",
    "all_time_low": 285,
    "updated": "2026-06-16",
    "credit": 100,
    "credit_inferred": true
  },
  "four seasons hotel seoul": {
    "price": 454,
    "name": "Four Seasons Hotel Seoul",
    "earliest": "2027-02-04",
    "all_time_low": 432,
    "updated": "2026-06-16",
    "credit": 100,
    "credit_inferred": true
  },
  "paradise hotel busan": {
    "price": 158,
    "name": "Paradise Hotel Busan",
    "earliest": "2026-09-01",
    "all_time_low": 153,
    "updated": "2026-06-16",
    "credit": 100,
    "credit_inferred": true
  },
  "signiel busan": {
    "price": 210,
    "name": "SIGNIEL BUSAN",
    "earliest": "2026-12-01",
    "all_time_low": 195,
    "updated": "2026-06-16",
    "credit": 100,
    "credit_inferred": true
  },
  "jw marriott jeju resort spa": {
    "price": 724,
    "name": "JW Marriott Jeju Resort & Spa",
    "earliest": "2026-06-22",
    "all_time_low": 607,
    "updated": "2026-06-16",
    "credit": 100,
    "credit_inferred": true
  }
}